autobazaar/__init__.py
autobazaar/__main__.py
autobazaar/pipeline.py
autobazaar/search.py
autobazaar/utils.py
autobazaar/templates/graph.community_detection.default.json
autobazaar/templates/graph.graph_matching.default.json
autobazaar/templates/graph.link_prediction.default.json
autobazaar/templates/graph.vertex_nomination.default.json
autobazaar/templates/image.classification.default.json
autobazaar/templates/image.regression.default.json
autobazaar/templates/multi_table.classification.default.json
autobazaar/templates/multi_table.regression.default.json
autobazaar/templates/single_table.classification.default.json
autobazaar/templates/single_table.classification.dfs.json
autobazaar/templates/single_table.classification.encoding.json
autobazaar/templates/single_table.classification.random_forest.json
autobazaar/templates/single_table.collaborative_filtering.default.json
autobazaar/templates/single_table.regression.default.json
autobazaar/templates/single_table.regression.dfs.json
autobazaar/templates/single_table.regression.encoding.json
autobazaar/templates/single_table.time_series_forecasting.default.json
autobazaar/templates/text.classification.default.json
autobazaar/templates/text.classification.lstm.json
autobazaar/templates/text.regression.default.json
autobazaar/templates/timeseries.classification.default.json
autobazaar/templates/timeseries.regression.default.json
autobazaar-0.2.1.dist-info/AUTHORS.rst
autobazaar-0.2.1.dist-info/LICENSE
autobazaar-0.2.1.dist-info/METADATA
autobazaar-0.2.1.dist-info/WHEEL
autobazaar-0.2.1.dist-info/entry_points.txt
autobazaar-0.2.1.dist-info/top_level.txt
autobazaar-0.2.1.dist-info/RECORD
