Metadata-Version: 2.1
Name: autobazaar
Version: 0.2.1
Summary: The Machine Learning Bazaar
Home-page: https://github.com/HDI-project/AutoBazaar
Author: MIT Data To AI Lab
Author-email: dailabmit@gmail.com
License: MIT license
Keywords: automl machine learning hyperparameters tuning classification regression autobazaar
Platform: UNKNOWN
Classifier: Development Status :: 3 - Alpha
Classifier: Intended Audience :: Developers
Classifier: License :: OSI Approved :: MIT License
Classifier: Natural Language :: English
Classifier: Programming Language :: Python :: 3
Classifier: Programming Language :: Python :: 3.6
Classifier: Programming Language :: Python :: 3.7
Classifier: Topic :: Scientific/Engineering :: Artificial Intelligence
Requires-Python: >=3.5,<3.8
Requires-Dist: mlblocks (<0.4,>=0.3.2)
Requires-Dist: mlprimitives (<0.3,>=0.2.2)
Requires-Dist: baytune (<0.3,>=0.2.1)
Requires-Dist: mit-d3m (<0.3,>=0.2.1)
Requires-Dist: gitpython (<4,>=3.1.1)
Requires-Dist: Keras (<2.4,>=2.1.6)
Requires-Dist: scikit-learn (<0.21,>=0.20.0)
Requires-Dist: pandas (<0.25,>=0.23.4)
Requires-Dist: numpy (<1.17,>=1.15.2)
Requires-Dist: python-dateutil (<2.8.1,>=2.1)
Provides-Extra: dev
Requires-Dist: pip (>=9.0.1) ; extra == 'dev'
Requires-Dist: bumpversion (<0.6,>=0.5.3) ; extra == 'dev'
Requires-Dist: watchdog (<0.11,>=0.8.3) ; extra == 'dev'
Requires-Dist: m2r (<0.3,>=0.2.0) ; extra == 'dev'
Requires-Dist: autodocsumm (<0.2,>=0.1.10) ; extra == 'dev'
Requires-Dist: Sphinx (<3,>=1.7.1) ; extra == 'dev'
Requires-Dist: sphinx-rtd-theme (<0.5,>=0.2.4) ; extra == 'dev'
Requires-Dist: flake8 (<4,>=3.7.7) ; extra == 'dev'
Requires-Dist: isort (<5,>=4.3.4) ; extra == 'dev'
Requires-Dist: autoflake (<2,>=1.1) ; extra == 'dev'
Requires-Dist: autopep8 (<2,>=1.4.3) ; extra == 'dev'
Requires-Dist: twine (<4,>=1.10.0) ; extra == 'dev'
Requires-Dist: wheel (>=0.30.0) ; extra == 'dev'
Requires-Dist: coverage (<6,>=4.5.1) ; extra == 'dev'
Requires-Dist: tox (<4,>=2.9.1) ; extra == 'dev'
Requires-Dist: rundoc (<0.5,>=0.4.3) ; extra == 'dev'
Requires-Dist: pytest (>=3.4.2) ; extra == 'dev'
Requires-Dist: pytest-cov (>=2.6.0) ; extra == 'dev'
Provides-Extra: test
Requires-Dist: pytest (>=3.4.2) ; extra == 'test'
Requires-Dist: pytest-cov (>=2.6.0) ; extra == 'test'
Requires-Dist: rundoc (<0.5,>=0.4.3) ; extra == 'test'
